bergtalzug/__init__.py
bergtalzug/etl_pipeline.py
bergtalzug/py.typed
bergtalzug-0.2.0.dist-info/WHEEL
bergtalzug-0.2.0.dist-info/METADATA
bergtalzug-0.2.0.dist-info/RECORD
