Metadata-Version: 2.3
Name: bergtalzug
Version: 0.2.0
Summary: Monorepo for bergtalzug
Requires-Dist: culsans>=0.9.0
Requires-Dist: pydantic>=2.11.7
Requires-Python: >=3.14
